mat_dp_core/__init__.py
mat_dp_core/further_constraints.py
mat_dp_core/maths_core/__init__.py
mat_dp_core/maths_core/constraints.py
mat_dp_core/maths_core/exceptions.py
mat_dp_core/maths_core/processes.py
mat_dp_core/maths_core/resources.py
mat_dp_core/maths_core/solve.py
mat_dp_core/maths_core/solvers.py
mat_dp_core/maths_core/tools.py
mat_dp_core/measure.py
mat_dp_core-0.1.1.dist-info/LICENSE.md
mat_dp_core-0.1.1.dist-info/WHEEL
mat_dp_core-0.1.1.dist-info/METADATA
mat_dp_core-0.1.1.dist-info/RECORD
