Metadata-Version: 2.1
Name: mat-dp-core
Version: 0.1.1
Summary: 
License: MIT
Author: Edd Salkield
Author-email: edd@salkield.uk
Requires-Python: >=3.9,<3.10
Classifier: License :: OSI Approved :: MIT License
Classifier: Programming Language :: Python :: 3
Classifier: Programming Language :: Python :: 3.9
Requires-Dist: numpy (>=1.23.0,<2.0.0)
Requires-Dist: scipy (>=1.7.1,<2.0.0)
